wtfport/__init__.py
wtfport/cli.py
wtfport/core.py
wtfport/log_tail.py
wtfport/notifier.py
wtfport/output.py
wtfport/platform_utils.py
wtfport/stats.py
wtfport-0.1.1.dist-info/METADATA
wtfport-0.1.1.dist-info/WHEEL
wtfport-0.1.1.dist-info/entry_points.txt
wtfport-0.1.1.dist-info/top_level.txt
wtfport-0.1.1.dist-info/RECORD
