Metadata-Version: 2.4
Name: wtfport
Version: 0.1.1
Summary: CLI tool to watch system port usage
Author-email: Henry <henry@example.com>
License: MIT
Project-URL: Homepage, https://github.com/yourname/wtfport
Project-URL: Issues, https://github.com/yourname/wtfport/issues
Keywords: ports,network,cli
Classifier: Development Status :: 4 - Beta
Classifier: Environment :: Console
Classifier: Intended Audience :: Developers
Classifier: Intended Audience :: System Administrators
Classifier: License :: OSI Approved :: MIT License
Classifier: Operating System :: OS Independent
Classifier: Programming Language :: Python :: 3
Classifier: Programming Language :: Python :: 3.7
Classifier: Programming Language :: Python :: 3.8
Classifier: Programming Language :: Python :: 3.9
Classifier: Programming Language :: Python :: 3.10
Classifier: Programming Language :: Python :: 3.11
Classifier: Programming Language :: Python :: 3.12
Classifier: Programming Language :: Python :: 3.13
Classifier: Topic :: Software Development :: Debuggers
Classifier: Topic :: System :: Networking
Classifier: Topic :: Utilities
Requires-Python: >=3.7
Requires-Dist: psutil
Requires-Dist: click
Provides-Extra: dev
Requires-Dist: build; extra == "dev"
Requires-Dist: twine; extra == "dev"
Requires-Dist: pytest; extra == "dev"
